Workbook

Sheet Financial Data
A1: Month | B1: Month_Num | C1: Cost_Centre | D1: Revenue | E1: COGS | F1: Gross_Profit | G1: Operating_Expenses | H1: EBITDA | I1: Forecast_Revenue | J1: Forecast_OpEx
A2: Jan | B2: 1 | C2: Operations | D2: 183055 | E2: 69836 | F2: =D2-E2 -> 113219 | G2: 52883 | H2: =F2-G2 -> 60336 | I2: 180900 | J2: 52156
A3: Jan | B3: 1 | C3: Marketing | D3: 94881 | E3: 37325 | F3: =D3-E3 -> 57556 | G3: 37953 | H3: =F3-G3 -> 19603 | I3: 95475 | J3: 38114
A4: Jan | B4: 1 | C4: Technology | D4: 143055 | E4: 60169 | F4: =D4-E4 -> 82886 | G4: 45982 | H4: =F4-G4 -> 36904 | I4: 140700 | J4: 45135
A5: Jan | B5: 1 | C5: HR | D5: 61777 | E5: 23798 | F5: =D5-E5 -> 37979 | G5: 28829 | H5: =F5-G5 -> 9150 | I5: 60300 | J5: 28084
A6: Jan | B6: 1 | C6: Finance | D6: 75457 | E6: 28809 | F6: =D6-E6 -> 46648 | G6: 22134 | H6: =F6-G6 -> 24514 | I6: 75375 | J6: 22066
A7: Feb | B7: 2 | C7: Operations | D7: 180168 | E7: 73927 | F7: =D7-E7 -> 106241 | G7: 52048 | H7: =F7-G7 -> 54193 | I7: 181800 | J7: 52312
A8: Feb | B8: 2 | C8: Marketing | D8: 94176 | E8: 36910 | F8: =D8-E8 -> 57266 | G8: 37670 | H8: =F8-G8 -> 19596 | I8: 95950 | J8: 38228
A9: Feb | B9: 2 | C9: Technology | D9: 143149 | E9: 59077 | F9: =D9-E9 -> 84072 | G9: 46012 | H9: =F9-G9 -> 38060 | I9: 141400 | J9: 45270
A10: Feb | B10: 2 | C10: HR | D10: 60061 | E10: 24947 | F10: =D10-E10 -> 35114 | G10: 28029 | H10: =F10-G10 -> 7085 | I10: 60600 | J10: 28168
A11: Feb | B11: 2 | C11: Finance | D11: 77285 | E11: 29398 | F11: =D11-E11 -> 47887 | G11: 22670 | H11: =F11-G11 -> 25217 | I11: 75750 | J11: 22132
A12: Mar | B12: 3 | C12: Operations | D12: 186352 | E12: 78620 | F12: =D12-E12 -> 107732 | G12: 53835 | H12: =F12-G12 -> 53897 | I12: 182700 | J12: 52468
A13: Mar | B13: 3 | C13: Marketing | D13: 96141 | E13: 37430 | F13: =D13-E13 -> 58711 | G13: 38456 | H13: =F13-G13 -> 20255 | I13: 96425 | J13: 38342
... A61: Dec | B61: 12 | C61: Finance | D61: 80284 | E61: 31244 | F61: =D61-E61 -> 49040 | G61: 23550 | H61: =F61-G61 -> 25490 | I61: 79500 | J61: 22792

Sheet KPI Summary
A1: Month | B1: Month_Num | C1: Total_Revenue | D1: Total_COGS | E1: Total_Gross_Profit | F1: Total_OpEx | G1: Total_EBITDA | H1: Gross_Margin_% | I1: EBITDA_Margin_% | J1: Forecast_Revenue | K1: Revenue_vs_Forecast_% | L1: Forecast_OpEx | M1: OpEx_vs_Forecast_%
A2: Jan | B2: 1 | C2: =SUMIF('Financial Data'!A:A,A2,'Financial Data'!D:D) -> 558225 | D2: =SUMIF('Financial Data'!A:A,A2,'Financial Data'!E:E) -> 219937 | E2: =C2-D2 -> 338288 | F2: =SUMIF('Financial Data'!A:A,A2,'Financial Data'!G:G) -> 187781 | G2: =E2-F2 -> 150507 | H2: =E2/C2 -> 0.60600654 | I2: =G2/C2 -> 0.26961709 | J2: =SUMIF('Financial Data'!A:A,A2,'Financial Data'!I:I) -> 552750 | K2: =(C2-J2)/J2 -> 0.0099050204 | L2: =SUMIF('Financial Data'!A:A,A2,'Financial Data'!J:J) -> 185555 | M2: =(F2-L2)/L2 -> 0.011996443
A3: Feb | B3: 2 | C3: =SUMIF('Financial Data'!A:A,A3,'Financial Data'!D:D) -> 554839 | D3: =SUMIF('Financial Data'!A:A,A3,'Financial Data'!E:E) -> 224259 | E3: =C3-D3 -> 330580 | F3: =SUMIF('Financial Data'!A:A,A3,'Financial Data'!G:G) -> 186429 | G3: =E3-F3 -> 144151 | H3: =E3/C3 -> 0.59581248 | I3: =G3/C3 -> 0.2598069 | J3: =SUMIF('Financial Data'!A:A,A3,'Financial Data'!I:I) -> 555500 | K3: =(C3-J3)/J3 -> -0.001189919 | L3: =SUMIF('Financial Data'!A:A,A3,'Financial Data'!J:J) -> 186110 | M3: =(F3-L3)/L3 -> 0.0017140401
A4: Mar | B4: 3 | C4: =SUMIF('Financial Data'!A:A,A4,'Financial Data'!D:D) -> 566274 | D4: =SUMIF('Financial Data'!A:A,A4,'Financial Data'!E:E) -> 230002 | E4: =C4-D4 -> 336272 | F4: =SUMIF('Financial Data'!A:A,A4,'Financial Data'!G:G) -> 190032 | G4: =E4-F4 -> 146240 | H4: =E4/C4 -> 0.59383267 | I4: =G4/C4 -> 0.25824954 | J4: =SUMIF('Financial Data'!A:A,A4,'Financial Data'!I:I) -> 558250 | K4: =(C4-J4)/J4 -> 0.014373489 | L4: =SUMIF('Financial Data'!A:A,A4,'Financial Data'!J:J) -> 186665 | M4: =(F4-L4)/L4 -> 0.018037661
A5: Apr | B5: 4 | C5: =SUMIF('Financial Data'!A:A,A5,'Financial Data'!D:D) -> 568180 | D5: =SUMIF('Financial Data'!A:A,A5,'Financial Data'!E:E) -> 239556 | E5: =C5-D5 -> 328624 | F5: =SUMIF('Financial Data'!A:A,A5,'Financial Data'!G:G) -> 191079 | G5: =E5-F5 -> 137545 | H5: =E5/C5 -> 0.57838009 | I5: =G5/C5 -> 0.24207997 | J5: =SUMIF('Financial Data'!A:A,A5,'Financial Data'!I:I) -> 561000 | K5: =(C5-J5)/J5 -> 0.012798574 | L5: =SUMIF('Financial Data'!A:A,A5,'Financial Data'!J:J) -> 187220 | M5: =(F5-L5)/L5 -> 0.020612114
A6: May | B6: 5 | C6: =SUMIF('Financial Data'!A:A,A6,'Financial Data'!D:D) -> 563420 | D6: =SUMIF('Financial Data'!A:A,A6,'Financial Data'!E:E) -> 220977 | E6: =C6-D6 -> 342443 | F6: =SUMIF('Financial Data'!A:A,A6,'Financial Data'!G:G) -> 189210 | G6: =E6-F6 -> 153233 | H6: =E6/C6 -> 0.60779348 | I6: =G6/C6 -> 0.2719694 | J6: =SUMIF('Financial Data'!A:A,A6,'Financial Data'!I:I) -> 563750 | K6: =(C6-J6)/J6 -> -0.00058536585 | L6: =SUMIF('Financial Data'!A:A,A6,'Financial Data'!J:J) -> 187775 | M6: =(F6-L6)/L6 -> 0.0076421249
A7: Jun | B7: 6 | C7: =SUMIF('Financial Data'!A:A,A7,'Financial Data'!D:D) -> 565762 | D7: =SUMIF('Financial Data'!A:A,A7,'Financial Data'!E:E) -> 232525 | E7: =C7-D7 -> 333237 | F7: =SUMIF('Financial Data'!A:A,A7,'Financial Data'!G:G) -> 197685 | G7: =E7-F7 -> 135552 | H7: =E7/C7 -> 0.58900562 | I7: =G7/C7 -> 0.23959191 | J7: =SUMIF('Financial Data'!A:A,A7,'Financial Data'!I:I) -> 566500 | K7: =(C7-J7)/J7 -> -0.0013027361 | L7: =SUMIF('Financial Data'!A:A,A7,'Financial Data'!J:J) -> 188330 | M7: =(F7-L7)/L7 -> 0.049673446
A8: Jul | B8: 7 | C8: =SUMIF('Financial Data'!A:A,A8,'Financial Data'!D:D) -> 577572 | D8: =SUMIF('Financial Data'!A:A,A8,'Financial Data'!E:E) -> 239157 | E8: =C8-D8 -> 338415 | F8: =SUMIF('Financial Data'!A:A,A8,'Financial Data'!G:G) -> 201719 | G8: =E8-F8 -> 136696 | H8: =E8/C8 -> 0.58592695 | I8: =G8/C8 -> 0.23667352 | J8: =SUMIF('Financial Data'!A:A,A8,'Financial Data'!I:I) -> 569250 | K8: =(C8-J8)/J8 -> 0.014619236 | L8: =SUMIF('Financial Data'!A:A,A8,'Financial Data'!J:J) -> 188885 | M8: =(F8-L8)/L8 -> 0.067946105
A9: Aug | B9: 8 | C9: =SUMIF('Financial Data'!A:A,A9,'Financial Data'!D:D) -> 575387 | D9: =SUMIF('Financial Data'!A:A,A9,'Financial Data'!E:E) -> 237455 | E9: =C9-D9 -> 337932 | F9: =SUMIF('Financial Data'!A:A,A9,'Financial Data'!G:G) -> 201462 | G9: =E9-F9 -> 136470 | H9: =E9/C9 -> 0.58731254 | I9: =G9/C9 -> 0.2371795 | J9: =SUMIF('Financial Data'!A:A,A9,'Financial Data'!I:I) -> 572000 | K9: =(C9-J9)/J9 -> 0.0059213287 | L9: =SUMIF('Financial Data'!A:A,A9,'Financial Data'!J:J) -> 189440 | M9: =(F9-L9)/L9 -> 0.063460726
A10: Sep | B10: 9 | C10: =SUMIF('Financial Data'!A:A,A10,'Financial Data'!D:D) -> 577709 | D10: =SUMIF('Financial Data'!A:A,A10,'Financial Data'!E:E) -> 232028 | E10: =C10-D10 -> 345681 | F10: =SUMIF('Financial Data'!A:A,A10,'Financial Data'!G:G) -> 202258 | G10: =E10-F10 -> 143423 | H10: =E10/C10 -> 0.59836527 | I10: =G10/C10 -> 0.24826167 | J10: =SUMIF('Financial Data'!A:A,A10,'Financial Data'!I:I) -> 574750 | K10: =(C10-J10)/J10 -> 0.0051483254 | L10: =SUMIF('Financial Data'!A:A,A10,'Financial Data'!J:J) -> 189995 | M10: =(F10-L10)/L10 -> 0.064543804
A11: Oct | B11: 10 | C11: =SUMIF('Financial Data'!A:A,A11,'Financial Data'!D:D) -> 578324 | D11: =SUMIF('Financial Data'!A:A,A11,'Financial Data'!E:E) -> 238900 | E11: =C11-D11 -> 339424 | F11: =SUMIF('Financial Data'!A:A,A11,'Financial Data'!G:G) -> 202484 | G11: =E11-F11 -> 136940 | H11: =E11/C11 -> 0.58690976 | I11: =G11/C11 -> 0.23678768 | J11: =SUMIF('Financial Data'!A:A,A11,'Financial Data'!I:I) -> 577500 | K11: =(C11-J11)/J11 -> 0.0014268398 | L11: =SUMIF('Financial Data'!A:A,A11,'Financial Data'!J:J) -> 190550 | M11: =(F11-L11)/L11 -> 0.062629231
A12: Nov | B12: 11 | C12: =SUMIF('Financial Data'!A:A,A12,'Financial Data'!D:D) -> 576495 | D12: =SUMIF('Financial Data'!A:A,A12,'Financial Data'!E:E) -> 242214 | E12: =C12-D12 -> 334281 | F12: =SUMIF('Financial Data'!A:A,A12,'Financial Data'!G:G) -> 201594 | G12: =E12-F12 -> 132687 | H12: =E12/C12 -> 0.57985065 | I12: =G12/C12 -> 0.23016158 | J12: =SUMIF('Financial Data'!A:A,A12,'Financial Data'!I:I) -> 580250 | K12: =(C12-J12)/J12 -> -0.0064713486 | L12: =SUMIF('Financial Data'!A:A,A12,'Financial Data'!J:J) -> 191105 | M12: =(F12-L12)/L12 -> 0.054886057
A13: Dec | B13: 12 | C13: =SUMIF('Financial Data'!A:A,A13,'Financial Data'!D:D) -> 591828 | D13: =SUMIF('Financial Data'!A:A,A13,'Financial Data'!E:E) -> 240164 | E13: =C13-D13 -> 351664 | F13: =SUMIF('Financial Data'!A:A,A13,'Financial Data'!G:G) -> 206659 | G13: =E13-F13 -> 145005 | H13: =E13/C13 -> 0.59419967 | I13: =G13/C13 -> 0.24501206 | J13: =SUMIF('Financial Data'!A:A,A13,'Financial Data'!I:I) -> 583000 | K13: =(C13-J13)/J13 -> 0.015142367 | L13: =SUMIF('Financial Data'!A:A,A13,'Financial Data'!J:J) -> 191660 | M13: =(F13-L13)/L13 -> 0.078258374
